hipopy/__init__.py
hipopy/hipopy.py
hipopy-2.0.1.dist-info/METADATA
hipopy-2.0.1.dist-info/WHEEL
hipopy-2.0.1.dist-info/licenses/LICENSE
hipopy-2.0.1.dist-info/RECORD
