Metadata-Version: 2.4
Name: hipopy
Version: 2.0.1
Summary: UpROOT-Like I/O Interface for CLAS12 HIPO Files
License: MIT
License-File: LICENSE
Author: Matthew McEneaney
Author-email: matthew.mceneaney@duke.edu
Requires-Python: >=3.9.0
Classifier: License :: OSI Approved :: MIT License
Classifier: Programming Language :: Python :: 3
Classifier: Programming Language :: Python :: 3.9
Classifier: Programming Language :: Python :: 3.10
Classifier: Programming Language :: Python :: 3.11
Classifier: Programming Language :: Python :: 3.12
Classifier: Programming Language :: Python :: 3.13
Classifier: Programming Language :: Python :: 3.14
Requires-Dist: hipopybind (>=2.0.1)
Requires-Dist: numpy (>=2.0.0)
Project-URL: Repository, https://github.com/mfmceneaney/hipopy.git
